{
    "reconstructed_state": [
        [
            {
                "real": 0.006091870839922087,
                "imag": 0.0
            },
            {
                "real": 0.04023056032899624,
                "imag": -0.05506582191166892
            }
        ],
        [
            {
                "real": 0.04023056032899624,
                "imag": 0.05506582191166892
            },
            {
                "real": 0.9939081291603268,
                "imag": 0.0
            }
        ]
    ],
    "target_state": [
        [
            {
                "real": 3.749399456654643e-33,
                "imag": 0.0
            },
            {
                "real": -3.135358277449929e-17,
                "imag": -5.259612441860393e-17
            }
        ],
        [
            {
                "real": -3.135358277449929e-17,
                "imag": 5.259612441860393e-17
            },
            {
                "real": 0.9999999999999991,
                "imag": 0.0
            }
        ]
    ],
    "fidelity": 0.9939,
    "purity": 0.9972
}