{
    "reconstructed_state": [
        [
            {
                "real": 0.961324173008756,
                "imag": 0.0
            },
            {
                "real": 0.05546550914942968,
                "imag": -0.18467155895736348
            }
        ],
        [
            {
                "real": 0.05546550914942968,
                "imag": 0.18467155895736348
            },
            {
                "real": 0.0386758269914117,
                "imag": 0.0
            }
        ]
    ],
    "target_state": [
        [
            {
                "real": 0.961939766255643,
                "imag": 0.0
            },
            {
                "real": 0.046937536206303004,
                "imag": -0.18549533699412302
            }
        ],
        [
            {
                "real": 0.046937536206303004,
                "imag": 0.18549533699412302
            },
            {
                "real": 0.038060233744356006,
                "imag": 0.0
            }
        ]
    ],
    "fidelity": 0.9999,
    "purity": 1.0
}