{
    "reconstructed_state": [
        [
            {
                "real": 0.9614481935269198,
                "imag": 0.0
            },
            {
                "real": 0.11799262778130659,
                "imag": -0.15212923596552355
            }
        ],
        [
            {
                "real": 0.11799262778130659,
                "imag": 0.15212923596552355
            },
            {
                "real": 0.03855180647347395,
                "imag": 0.0
            }
        ]
    ],
    "target_state": [
        [
            {
                "real": 0.961939766255643,
                "imag": 0.0
            },
            {
                "real": 0.11435062125614101,
                "imag": -0.153413127762965
            }
        ],
        [
            {
                "real": 0.11435062125614101,
                "imag": 0.153413127762965
            },
            {
                "real": 0.038060233744356006,
                "imag": 0.0
            }
        ]
    ],
    "fidelity": 1.0,
    "purity": 1.0
}