{
    "reconstructed_state": [
        [
            {
                "real": 0.717779318605066,
                "imag": 0.0
            },
            {
                "real": 0.06320796991485277,
                "imag": -0.06751295288748747
            }
        ],
        [
            {
                "real": 0.06320796991485277,
                "imag": 0.06751295288748747
            },
            {
                "real": 0.28222068139487877,
                "imag": 0.0
            }
        ]
    ],
    "target_state": [
        [
            {
                "real": 1.0000000000000002,
                "imag": 0.0
            },
            {
                "real": 0.0,
                "imag": 0.0
            }
        ],
        [
            {
                "real": 0.0,
                "imag": -0.0
            },
            {
                "real": 0.0,
                "imag": 0.0
            }
        ]
    ],
    "fidelity": 0.7178,
    "purity": 0.612
}