{
    "reconstructed_state": [
        [
            {
                "real": 0.5251411027352856,
                "imag": 0.0
            },
            {
                "real": 0.1439436269833822,
                "imag": 0.47438569355818877
            }
        ],
        [
            {
                "real": 0.1439436269833822,
                "imag": -0.47438569355818877
            },
            {
                "real": 0.47485889726474917,
                "imag": 0.0
            }
        ]
    ],
    "target_state": [
        [
            {
                "real": 0.4999999999999999,
                "imag": 0.0
            },
            {
                "real": 0.0,
                "imag": -0.4999999999999999
            }
        ],
        [
            {
                "real": 0.0,
                "imag": 0.4999999999999999
            },
            {
                "real": 0.4999999999999999,
                "imag": 0.0
            }
        ]
    ],
    "fidelity": 0.0256,
    "purity": 0.9928
}