{
    "reconstructed_state": [
        [
            {
                "real": 0.9954249334567509,
                "imag": 0.0
            },
            {
                "real": 0.025352265912956983,
                "imag": -0.010941128939539736
            }
        ],
        [
            {
                "real": 0.025352265912956983,
                "imag": 0.010941128939539736
            },
            {
                "real": 0.004575066543216238,
                "imag": 0.0
            }
        ]
    ],
    "target_state": [
        [
            {
                "real": 1.0,
                "imag": 0.0
            },
            {
                "real": 0.0,
                "imag": 0.0
            }
        ],
        [
            {
                "real": 0.0,
                "imag": 0.0
            },
            {
                "real": 0.0,
                "imag": 0.0
            }
        ]
    ],
    "fidelity": 0.9954,
    "purity": 0.9924
}