{
    "reconstructed_state": [
        [
            {
                "real": 0.9838122117373242,
                "imag": 0.0
            },
            {
                "real": 0.03187420321875509,
                "imag": -0.025828892526523272
            }
        ],
        [
            {
                "real": 0.03187420321875509,
                "imag": 0.025828892526523272
            },
            {
                "real": 0.016187788262721346,
                "imag": 0.0
            }
        ]
    ],
    "target_state": [
        [
            {
                "real": 0.9999999999999997,
                "imag": 0.0
            },
            {
                "real": 0.0,
                "imag": 0.0
            }
        ],
        [
            {
                "real": 0.0,
                "imag": 0.0
            },
            {
                "real": 0.0,
                "imag": 0.0
            }
        ]
    ],
    "fidelity": 0.9838,
    "purity": 0.9715
}