{
    "reconstructed_state": [
        [
            {
                "real": 0.5235381620582366,
                "imag": 0.0
            },
            {
                "real": -0.3442485099184329,
                "imag": -0.3422244526003497
            }
        ],
        [
            {
                "real": -0.3442485099184329,
                "imag": 0.3422244526003497
            },
            {
                "real": 0.4764618379417608,
                "imag": 0.0
            }
        ]
    ],
    "target_state": [
        [
            {
                "real": 0.5,
                "imag": 0.0
            },
            {
                "real": 0.17755348120406803,
                "imag": 0.46741283819800705
            }
        ],
        [
            {
                "real": 0.17755348120406803,
                "imag": -0.46741283819800705
            },
            {
                "real": 0.49999999999999906,
                "imag": 0.0
            }
        ]
    ],
    "fidelity": 0.0578,
    "purity": 0.9724
}