{
    "reconstructed_state": [
        [
            {
                "real": 0.008711541063847536,
                "imag": 0.0
            },
            {
                "real": 0.04305685157389941,
                "imag": -0.06512329250067156
            }
        ],
        [
            {
                "real": 0.04305685157389941,
                "imag": 0.06512329250067156
            },
            {
                "real": 0.991288458936172,
                "imag": 0.0
            }
        ]
    ],
    "target_state": [
        [
            {
                "real": 0.0,
                "imag": 0.0
            },
            {
                "real": 0.0,
                "imag": 0.0
            }
        ],
        [
            {
                "real": 0.0,
                "imag": -0.0
            },
            {
                "real": 1.0000000000000004,
                "imag": 0.0
            }
        ]
    ],
    "fidelity": 0.9913,
    "purity": 0.9949
}