{
    "reconstructed_state": [
        [
            {
                "real": 0.17652698631424724,
                "imag": 0.0
            },
            {
                "real": -0.009178265950119495,
                "imag": -0.3654069373303782
            }
        ],
        [
            {
                "real": -0.009178265950119495,
                "imag": 0.3654069373303782
            },
            {
                "real": 0.823473013685935,
                "imag": 0.0
            }
        ]
    ],
    "target_state": [
        [
            {
                "real": 0.14644660940672602,
                "imag": 0.0
            },
            {
                "real": -0.051037624317058,
                "imag": -0.349850197804818
            }
        ],
        [
            {
                "real": -0.051037624317058,
                "imag": 0.349850197804818
            },
            {
                "real": 0.8535533905932731,
                "imag": 0.0
            }
        ]
    ],
    "fidelity": 0.9853,
    "purity": 0.9765
}