{
    "reconstructed_state": [
        [
            {
                "real": 0.015905566095328897,
                "imag": 0.0
            },
            {
                "real": 0.05623717909247451,
                "imag": -0.0584826405588951
            }
        ],
        [
            {
                "real": 0.05623717909247451,
                "imag": 0.0584826405588951
            },
            {
                "real": 0.9840944339046725,
                "imag": 0.0
            }
        ]
    ],
    "target_state": [
        [
            {
                "real": 3.7493994566546454e-33,
                "imag": 0.0
            },
            {
                "real": -6.000308264596574e-17,
                "imag": -1.2207765136831991e-17
            }
        ],
        [
            {
                "real": -6.000308264596574e-17,
                "imag": 1.2207765136831991e-17
            },
            {
                "real": 1.0,
                "imag": 0.0
            }
        ]
    ],
    "fidelity": 0.9841,
    "purity": 0.9819
}