{
    "reconstructed_state": [
        [
            {
                "real": 0.5357951480662584,
                "imag": 0.0
            },
            {
                "real": 0.20794884039705128,
                "imag": -0.04769825749417924
            },
            {
                "real": 0.2642427275528179,
                "imag": 0.042320123823911995
            },
            {
                "real": -0.01282495335043089,
                "imag": 0.004365773748197461
            }
        ],
        [
            {
                "real": 0.20794884039705128,
                "imag": 0.04769825749417924
            },
            {
                "real": 0.22508774256002542,
                "imag": 0.0
            },
            {
                "real": -0.007288549863158934,
                "imag": -0.014690749097775622
            },
            {
                "real": 0.002102396097553954,
                "imag": -0.00285538955216324
            }
        ],
        [
            {
                "real": 0.2642427275528179,
                "imag": -0.042320123823911995
            },
            {
                "real": -0.007288549863158934,
                "imag": 0.014690749097775622
            },
            {
                "real": 0.23795517195100307,
                "imag": 0.0
            },
            {
                "real": -0.01119927430148353,
                "imag": 0.008991313639123099
            }
        ],
        [
            {
                "real": -0.01282495335043089,
                "imag": -0.004365773748197461
            },
            {
                "real": 0.002102396097553954,
                "imag": 0.00285538955216324
            },
            {
                "real": -0.01119927430148353,
                "imag": -0.008991313639123099
            },
            {
                "real": 0.001161937435951374,
                "imag": 0.0
            }
        ]
    ],
    "target_state": [
        [
            {
                "real": 0.4999999999999999,
                "imag": 0.0
            },
            {
                "real": 0.0,
                "imag": 0.0
            },
            {
                "real": 0.4999999999999999,
                "imag": 0.0
            },
            {
                "real": 0.0,
                "imag": 0.0
            }
        ],
        [
            {
                "real": 0.0,
                "imag": 0.0
            },
            {
                "real": 0.0,
                "imag": 0.0
            },
            {
                "real": 0.0,
                "imag": 0.0
            },
            {
                "real": 0.0,
                "imag": 0.0
            }
        ],
        [
            {
                "real": 0.4999999999999999,
                "imag": 0.0
            },
            {
                "real": 0.0,
                "imag": 0.0
            },
            {
                "real": 0.4999999999999999,
                "imag": 0.0
            },
            {
                "real": 0.0,
                "imag": 0.0
            }
        ],
        [
            {
                "real": 0.0,
                "imag": 0.0
            },
            {
                "real": 0.0,
                "imag": 0.0
            },
            {
                "real": 0.0,
                "imag": 0.0
            },
            {
                "real": 0.0,
                "imag": 0.0
            }
        ]
    ],
    "fidelity": 0.6511,
    "purity": 0.63
}