{
    "reconstructed_state": [
        [
            {
                "real": 0.8550335110445905,
                "imag": 0.0
            },
            {
                "real": 0.2018098651559515,
                "imag": -0.28848567327774777
            }
        ],
        [
            {
                "real": 0.2018098651559515,
                "imag": 0.28848567327774777
            },
            {
                "real": 0.14496648895361897,
                "imag": 0.0
            }
        ]
    ],
    "target_state": [
        [
            {
                "real": 0.8535533905932736,
                "imag": 0.0
            },
            {
                "real": 0.26253482349814644,
                "imag": -0.23680258962012438
            }
        ],
        [
            {
                "real": 0.26253482349814644,
                "imag": 0.23680258962012438
            },
            {
                "real": 0.1464466094067262,
                "imag": 0.0
            }
        ]
    ],
    "fidelity": 0.9936,
    "purity": 1.0
}