{
    "reconstructed_state": [
        [
            {
                "real": 0.5128381331333259,
                "imag": 0.0
            },
            {
                "real": 0.41783866922057034,
                "imag": -0.20962273860143937
            }
        ],
        [
            {
                "real": 0.41783866922057034,
                "imag": 0.20962273860143937
            },
            {
                "real": 0.48716186686665763,
                "imag": 0.0
            }
        ]
    ],
    "target_state": [
        [
            {
                "real": 0.49999999999999983,
                "imag": 0.0
            },
            {
                "real": 0.37128030798630535,
                "imag": -0.3348894338458501
            }
        ],
        [
            {
                "real": 0.37128030798630535,
                "imag": 0.3348894338458501
            },
            {
                "real": 0.4999999999999998,
                "imag": 0.0
            }
        ]
    ],
    "fidelity": 0.9507,
    "purity": 0.9374
}