{
    "reconstructed_state": [
        [
            {
                "real": 0.1423210564870427,
                "imag": 0.0
            },
            {
                "real": 0.1009589771733549,
                "imag": -0.09718236376297382
            }
        ],
        [
            {
                "real": 0.1009589771733549,
                "imag": 0.09718236376297382
            },
            {
                "real": 0.8576789435129586,
                "imag": 0.0
            }
        ]
    ],
    "target_state": [
        [
            {
                "real": 1.0,
                "imag": 0.0
            },
            {
                "real": 0.0,
                "imag": 0.0
            }
        ],
        [
            {
                "real": 0.0,
                "imag": 0.0
            },
            {
                "real": 0.0,
                "imag": 0.0
            }
        ]
    ],
    "fidelity": 0.1423,
    "purity": 0.7951
}