{
    "reconstructed_state": [
        [
            {
                "real": 0.06502076654823205,
                "imag": 0.0
            },
            {
                "real": 0.1432741242424004,
                "imag": -0.20066288034002916
            }
        ],
        [
            {
                "real": 0.1432741242424004,
                "imag": 0.20066288034002916
            },
            {
                "real": 0.9349792334511161,
                "imag": 0.0
            }
        ]
    ],
    "target_state": [
        [
            {
                "real": 0.038060233744356006,
                "imag": 0.0
            },
            {
                "real": -0.159557144294624,
                "imag": 0.105608569994229
            }
        ],
        [
            {
                "real": -0.159557144294624,
                "imag": -0.105608569994229
            },
            {
                "real": 0.961939766255643,
                "imag": 0.0
            }
        ]
    ],
    "fidelity": 0.8138,
    "purity": 1.0
}