{
    "reconstructed_state": [
        [
            {
                "real": 0.2763277403936635,
                "imag": 0.0
            },
            {
                "real": 0.18369268716390538,
                "imag": -0.38537319532143144
            }
        ],
        [
            {
                "real": 0.18369268716390538,
                "imag": 0.38537319532143144
            },
            {
                "real": 0.7236722596061976,
                "imag": 0.0
            }
        ]
    ],
    "target_state": [
        [
            {
                "real": 0.3086582838174551,
                "imag": 0.0
            },
            {
                "real": -0.29195946833971853,
                "imag": 0.3579776759731077
            }
        ],
        [
            {
                "real": -0.29195946833971853,
                "imag": -0.3579776759731077
            },
            {
                "real": 0.6913417161825448,
                "imag": 0.0
            }
        ]
    ],
    "fidelity": 0.2024,
    "purity": 0.9646
}